{
  "name": "module.dashboard",
  "version": "0.0.1",
  "description": "App Dashboard",
  "author": "App Core",
  "web-pages":
  [
  	{
  		"id":"dashboard",
  		"title":"Dashboard",
  		"links":[
  			{
  				"id":"app.configuration",
  				"title":"Application Configurations",
  				"description":"Set/Modify application configurations"
  			},
  			{
  				"id":"app.admissions",
  				"title":"Admissions",
  				"description":"Manage Admissions"
  			}
  		]
  	} 
  ]
}